okfn_iati/__init__.py
okfn_iati/iati_schema_validator.py
okfn_iati/models.py
okfn_iati/multi_csv_converter.py
okfn_iati/organisation_xml_generator.py
okfn_iati/validators.py
okfn_iati/xml_comparator.py
okfn_iati/xml_generator.py
okfn_iati/data/CRSChannelCode.csv
okfn_iati/data/__init__.py
okfn_iati/data/location-type-codes.csv
okfn_iati/data/organisation_template.csv
okfn_iati/data/sector-category-codes.csv
okfn_iati/enums/__init__.py
okfn_iati/enums/sector_category.py
okfn_iati/schemas/2.03/iati-activities-schema.xsd
okfn_iati/schemas/2.03/iati-common.xsd
okfn_iati/schemas/2.03/iati-organisations-schema.xsd
okfn_iati/schemas/2.03/xml.xsd
okfn_iati-0.4.1.dist-info/licenses/LICENSE
okfn_iati-0.4.1.dist-info/METADATA
okfn_iati-0.4.1.dist-info/WHEEL
okfn_iati-0.4.1.dist-info/top_level.txt
okfn_iati-0.4.1.dist-info/RECORD
