Metadata-Version: 2.4
Name: okfn-iati
Version: 0.4.1
Summary: A Python library for working with IATI XML data according to the IATI 2.03 standard
Author-email: Open Knowledge Foundation <info@okfn.org>
Project-URL: Homepage, https://github.com/okfn/okfn_iati
Project-URL: Issues, https://github.com/okfn/okfn_iati/issues
Project-URL: Documentation, https://github.com/okfn/okfn_iati
Project-URL: Source Code, https://github.com/okfn/okfn_iati
Keywords: iati,xml,development,aid,transparency
Classifier: Development Status :: 4 - Beta
Classifier: Intended Audience :: Developers
Classifier: License :: OSI Approved :: MIT License
Classifier: Programming Language :: Python :: 3
Classifier: Programming Language :: Python :: 3.9
Classifier: Programming Language :: Python :: 3.10
Classifier: Programming Language :: Python :: 3.11
Classifier: Programming Language :: Python :: 3.12
Requires-Python: >=3.9
License-File: LICENSE
Requires-Dist: lxml>=4.9.0
Provides-Extra: dev
Requires-Dist: lxml>=4.9.0; extra == "dev"
Requires-Dist: build>=0.8.0; extra == "dev"
Requires-Dist: twine>=4.0.0; extra == "dev"
Requires-Dist: flake8>=6.0.0; extra == "dev"
Requires-Dist: pre-commit>=3.5.0; extra == "dev"
Dynamic: license-file
